{"fetched_at": 1784397014.8198884, "data": {"id": "48ca8f5f46eb95a95a448679ea6cf7b1", "sport_key": "baseball_mlb", "sport_title": "MLB", "commence_time": "2026-07-18T20:11:00Z", "home_team": "Houston Astros", "away_team": "Baltimore Orioles", "bookmakers": [{"key": "fanduel", "title": "FanDuel", "markets": [{"key": "pitcher_outs", "last_update": "2026-07-18T17:50:01Z", "outcomes": [{"name": "Over", "description": "Trevor Rogers", "price": 1.88, "point": 17.5}, {"name": "Under", "description": "Trevor Rogers", "price": 1.88, "point": 17.5}, {"name": "Over", "description": "Spencer Arrighetti", "price": 2.16, "point": 15.5}, {"name": "Under", "description": "Spencer Arrighetti", "price": 1.65, "point": 15.5}]}, {"key": "pitcher_strikeouts", "last_update": "2026-07-18T17:50:01Z", "outcomes": [{"name": "Over", "description": "Spencer Arrighetti", "price": 1.72, "point": 5.5}, {"name": "Under", "description": "Spencer Arrighetti", "price": 2.08, "point": 5.5}, {"name": "Over", "description": "Trevor Rogers", "price": 2.08, "point": 4.5}, {"name": "Under", "description": "Trevor Rogers", "price": 1.72, "point": 4.5}]}]}, {"key": "fanatics", "title": "Fanatics", "markets": [{"key": "pitcher_earned_runs", "last_update": "2026-07-18T17:49:32Z", "outcomes": [{"name": "Over", "description": "Spencer Arrighetti", "price": 1.95, "point": 2.5}, {"name": "Under", "description": "Spencer Arrighetti", "price": 1.74, "point": 2.5}]}, {"key": "pitcher_hits_allowed", "last_update": "2026-07-18T17:49:32Z", "outcomes": [{"name": "Over", "description": "Trevor Rogers", "price": 1.95, "point": 5.5}, {"name": "Under", "description": "Trevor Rogers", "price": 1.74, "point": 5.5}]}, {"key": "pitcher_outs", "last_update": "2026-07-18T17:49:32Z", "outcomes": [{"name": "Over", "description": "Spencer Arrighetti", "price": 2.2, "point": 15.5}, {"name": "Under", "description": "Spencer Arrighetti", "price": 1.59, "point": 15.5}]}, {"key": "pitcher_record_a_win", "last_update": "2026-07-18T17:49:32Z", "outcomes": [{"name": "Yes", "description": "Spencer Arrighetti", "price": 3.3}, {"name": "No", "description": "Spencer Arrighetti", "price": 1.29}]}, {"key": "pitcher_strikeouts", "last_update": "2026-07-18T17:49:32Z", "outcomes": [{"name": "Over", "description": "Spencer Arrighetti", "price": 1.67, "point": 5.5}, {"name": "Under", "description": "Spencer Arrighetti", "price": 2.15, "point": 5.5}]}]}, {"key": "draftkings", "title": "DraftKings", "markets": [{"key": "pitcher_earned_runs", "last_update": "2026-07-18T17:49:33Z", "outcomes": [{"name": "Over", "description": "Spencer Arrighetti", "price": 1.79, "point": 2.5}, {"name": "Under", "description": "Spencer Arrighetti", "price": 1.96, "point": 2.5}, {"name": "Over", "description": "Trevor Rogers", "price": 1.74, "point": 2.5}, {"name": "Under", "description": "Trevor Rogers", "price": 2.02, "point": 2.5}]}, {"key": "pitcher_hits_allowed", "last_update": "2026-07-18T17:49:33Z", "outcomes": [{"name": "Over", "description": "Spencer Arrighetti", "price": 1.98, "point": 4.5}, {"name": "Under", "description": "Spencer Arrighetti", "price": 1.77, "point": 4.5}, {"name": "Over", "description": "Trevor Rogers", "price": 2.0, "point": 5.5}, {"name": "Under", "description": "Trevor Rogers", "price": 1.76, "point": 5.5}]}, {"key": "pitcher_outs", "last_update": "2026-07-18T17:49:33Z", "outcomes": [{"name": "Over", "description": "Trevor Rogers", "price": 1.82, "point": 17.5}, {"name": "Under", "description": "Trevor Rogers", "price": 1.93, "point": 17.5}, {"name": "Over", "description": "Spencer Arrighetti", "price": 2.18, "point": 15.5}, {"name": "Under", "description": "Spencer Arrighetti", "price": 1.64, "point": 15.5}]}, {"key": "pitcher_record_a_win", "last_update": "2026-07-18T17:49:33Z", "outcomes": [{"name": "Yes", "description": "Trevor Rogers", "price": 2.31}, {"name": "No", "description": "Trevor Rogers", "price": 1.55}, {"name": "Yes", "description": "Spencer Arrighetti", "price": 3.25}, {"name": "No", "description": "Spencer Arrighetti", "price": 1.31}]}, {"key": "pitcher_strikeouts", "last_update": "2026-07-18T17:49:33Z", "outcomes": [{"name": "Over", "description": "Spencer Arrighetti", "price": 1.68, "point": 5.5}, {"name": "Under", "description": "Spencer Arrighetti", "price": 2.16, "point": 5.5}, {"name": "Over", "description": "Trevor Rogers", "price": 2.06, "point": 4.5}, {"name": "Under", "description": "Trevor Rogers", "price": 1.74, "point": 4.5}]}, {"key": "pitcher_walks", "last_update": "2026-07-18T17:49:33Z", "outcomes": [{"name": "Over", "description": "Trevor Rogers", "price": 1.67, "point": 1.5}, {"name": "Under", "description": "Trevor Rogers", "price": 2.13, "point": 1.5}, {"name": "Over", "description": "Spencer Arrighetti", "price": 1.78, "point": 2.5}, {"name": "Under", "description": "Spencer Arrighetti", "price": 1.97, "point": 2.5}]}]}, {"key": "williamhill_us", "title": "Caesars", "markets": [{"key": "pitcher_outs", "last_update": "2026-07-18T17:48:22Z", "outcomes": [{"name": "Over", "description": "Trevor Rogers", "price": 1.85, "point": 17.5}, {"name": "Under", "description": "Trevor Rogers", "price": 1.88, "point": 17.5}, {"name": "Over", "description": "Spencer Arrighetti", "price": 2.21, "point": 15.5}, {"name": "Under", "description": "Spencer Arrighetti", "price": 1.62, "point": 15.5}]}]}, {"key": "bovada", "title": "Bovada", "markets": [{"key": "pitcher_hits_allowed", "last_update": "2026-07-18T17:50:07Z", "outcomes": [{"name": "Over", "description": "Spencer Arrighetti", "price": 1.95, "point": 4.5}, {"name": "Under", "description": "Spencer Arrighetti", "price": 1.74, "point": 4.5}, {"name": "Over", "description": "Trevor Rogers", "price": 1.95, "point": 5.5}, {"name": "Under", "description": "Trevor Rogers", "price": 1.74, "point": 5.5}]}, {"key": "pitcher_outs", "last_update": "2026-07-18T17:50:07Z", "outcomes": [{"name": "Over", "description": "Spencer Arrighetti", "price": 2.2, "point": 15.5}, {"name": "Under", "description": "Spencer Arrighetti", "price": 1.62, "point": 15.5}, {"name": "Over", "description": "Trevor Rogers", "price": 1.8, "point": 17.5}, {"name": "Under", "description": "Trevor Rogers", "price": 1.87, "point": 17.5}]}, {"key": "pitcher_record_a_win", "last_update": "2026-07-18T17:50:07Z", "outcomes": [{"name": "Yes", "description": "Spencer Arrighetti", "price": 3.25}, {"name": "No", "description": "Spencer Arrighetti", "price": 1.29}, {"name": "Yes", "description": "Trevor Rogers", "price": 2.4}, {"name": "No", "description": "Trevor Rogers", "price": 1.56}]}, {"key": "pitcher_strikeouts", "last_update": "2026-07-18T17:50:07Z", "outcomes": [{"name": "Over", "description": "Spencer Arrighetti", "price": 1.67, "point": 5.5}, {"name": "Under", "description": "Spencer Arrighetti", "price": 2.15, "point": 5.5}, {"name": "Over", "description": "Trevor Rogers", "price": 2.1, "point": 4.5}, {"name": "Under", "description": "Trevor Rogers", "price": 1.69, "point": 4.5}]}, {"key": "pitcher_walks", "last_update": "2026-07-18T17:50:07Z", "outcomes": [{"name": "Over", "description": "Spencer Arrighetti", "price": 1.74, "point": 2.5}, {"name": "Under", "description": "Spencer Arrighetti", "price": 1.95, "point": 2.5}, {"name": "Over", "description": "Trevor Rogers", "price": 1.65, "point": 1.5}, {"name": "Under", "description": "Trevor Rogers", "price": 2.15, "point": 1.5}]}]}, {"key": "betmgm", "title": "BetMGM", "markets": [{"key": "pitcher_earned_runs", "last_update": "2026-07-18T17:49:43Z", "outcomes": [{"name": "Over", "description": "Trevor Rogers", "price": 1.74, "point": 2.5}, {"name": "Under", "description": "Trevor Rogers", "price": 1.95, "point": 2.5}, {"name": "Over", "description": "Spencer Arrighetti", "price": 1.95, "point": 2.5}, {"name": "Under", "description": "Spencer Arrighetti", "price": 1.74, "point": 2.5}]}, {"key": "pitcher_hits_allowed", "last_update": "2026-07-18T17:49:43Z", "outcomes": [{"name": "Over", "description": "Spencer Arrighetti", "price": 2.05, "point": 4.5}, {"name": "Under", "description": "Spencer Arrighetti", "price": 1.71, "point": 4.5}, {"name": "Over", "description": "Trevor Rogers", "price": 1.83, "point": 5.5}, {"name": "Under", "description": "Trevor Rogers", "price": 1.91, "point": 5.5}]}, {"key": "pitcher_outs", "last_update": "2026-07-18T17:49:43Z", "outcomes": [{"name": "Over", "description": "Trevor Rogers", "price": 1.91, "point": 17.5}, {"name": "Under", "description": "Trevor Rogers", "price": 1.8, "point": 17.5}, {"name": "Over", "description": "Spencer Arrighetti", "price": 2.25, "point": 15.5}, {"name": "Under", "description": "Spencer Arrighetti", "price": 1.61, "point": 15.5}]}, {"key": "pitcher_strikeouts", "last_update": "2026-07-18T17:49:43Z", "outcomes": [{"name": "Over", "description": "Spencer Arrighetti", "price": 1.67, "point": 5.5}, {"name": "Under", "description": "Spencer Arrighetti", "price": 2.1, "point": 5.5}, {"name": "Over", "description": "Trevor Rogers", "price": 1.95, "point": 4.5}, {"name": "Under", "description": "Trevor Rogers", "price": 1.8, "point": 4.5}]}]}, {"key": "betrivers", "title": "BetRivers", "markets": [{"key": "pitcher_outs", "last_update": "2026-07-18T17:49:28Z", "outcomes": [{"name": "Over", "description": "Spencer Arrighetti", "price": 2.17, "point": 15.5}, {"name": "Over", "description": "Trevor Rogers", "price": 1.83, "point": 17.5}]}, {"key": "pitcher_strikeouts", "last_update": "2026-07-18T17:49:28Z", "outcomes": [{"name": "Over", "description": "Trevor Rogers", "price": 2.07, "point": 4.5}, {"name": "Under", "description": "Trevor Rogers", "price": 1.71, "point": 4.5}, {"name": "Over", "description": "Spencer Arrighetti", "price": 1.66, "point": 5.5}, {"name": "Under", "description": "Spencer Arrighetti", "price": 2.14, "point": 5.5}]}]}]}}