{"fetched_at": 1782858897.2689667, "data": {"timestamp": "2025-05-04T17:35:38Z", "previous_timestamp": "2025-05-04T17:30:37Z", "next_timestamp": "2025-05-04T17:40:38Z", "data": {"id": "5ab936ada2e4c3e74ab88901221f0d7c", "sport_key": "baseball_mlb", "sport_title": "MLB", "commence_time": "2025-05-04T17:37:00Z", "home_team": "Toronto Blue Jays", "away_team": "Cleveland Guardians", "bookmakers": [{"key": "fanduel", "title": "FanDuel", "last_update": "2025-05-04T17:34:54Z", "markets": [{"key": "team_totals", "last_update": "2025-05-04T17:34:28Z", "outcomes": [{"name": "Over", "description": "Cleveland Guardians", "price": 2.12, "point": 4.5}, {"name": "Under", "description": "Cleveland Guardians", "price": 1.7, "point": 4.5}, {"name": "Over", "description": "Toronto Blue Jays", "price": 1.74, "point": 3.5}, {"name": "Under", "description": "Toronto Blue Jays", "price": 2.06, "point": 3.5}]}]}, {"key": "betonlineag", "title": "BetOnline.ag", "last_update": "2025-05-04T17:34:50Z", "markets": [{"key": "team_totals", "last_update": "2025-05-04T17:35:28Z", "outcomes": [{"name": "Over", "description": "Cleveland Guardians", "price": 2.15, "point": 4.5}, {"name": "Under", "description": "Cleveland Guardians", "price": 1.69, "point": 4.5}, {"name": "Over", "description": "Toronto Blue Jays", "price": 1.74, "point": 3.5}, {"name": "Under", "description": "Toronto Blue Jays", "price": 2.05, "point": 3.5}]}]}, {"key": "draftkings", "title": "DraftKings", "last_update": "2025-05-04T17:34:50Z", "markets": [{"key": "team_totals", "last_update": "2025-05-04T17:35:43Z", "outcomes": [{"name": "Over", "description": "Cleveland Guardians", "price": 2.05, "point": 4.5}, {"name": "Under", "description": "Cleveland Guardians", "price": 1.74, "point": 4.5}, {"name": "Over", "description": "Toronto Blue Jays", "price": 1.74, "point": 3.5}, {"name": "Under", "description": "Toronto Blue Jays", "price": 2.05, "point": 3.5}]}]}, {"key": "betrivers", "title": "BetRivers", "last_update": "2025-05-04T17:33:39Z", "markets": [{"key": "team_totals", "last_update": "2025-05-04T17:35:50Z", "outcomes": [{"name": "Over", "description": "Cleveland Guardians", "price": 1.62, "point": 3.5}, {"name": "Under", "description": "Cleveland Guardians", "price": 2.3, "point": 3.5}, {"name": "Over", "description": "Cleveland Guardians", "price": 2.08, "point": 4.5}, {"name": "Under", "description": "Cleveland Guardians", "price": 1.74, "point": 4.5}, {"name": "Over", "description": "Cleveland Guardians", "price": 2.8, "point": 5.5}, {"name": "Under", "description": "Cleveland Guardians", "price": 1.43, "point": 5.5}, {"name": "Over", "description": "Toronto Blue Jays", "price": 1.72, "point": 3.5}, {"name": "Under", "description": "Toronto Blue Jays", "price": 2.12, "point": 3.5}, {"name": "Over", "description": "Toronto Blue Jays", "price": 2.25, "point": 4.5}, {"name": "Under", "description": "Toronto Blue Jays", "price": 1.64, "point": 4.5}, {"name": "Over", "description": "Toronto Blue Jays", "price": 1.36, "point": 2.5}, {"name": "Under", "description": "Toronto Blue Jays", "price": 3.1, "point": 2.5}]}]}, {"key": "bovada", "title": "Bovada", "last_update": "2025-05-04T17:34:51Z", "markets": [{"key": "team_totals", "last_update": "2025-05-04T17:35:44Z", "outcomes": [{"name": "Over", "description": "Cleveland Guardians", "price": 2.1, "point": 4.5}, {"name": "Under", "description": "Cleveland Guardians", "price": 1.69, "point": 4.5}, {"name": "Over", "description": "Toronto Blue Jays", "price": 1.74, "point": 3.5}, {"name": "Under", "description": "Toronto Blue Jays", "price": 2.05, "point": 3.5}]}]}]}}}