{"fetched_at": 1784333657.4364932, "data": {"id": "cfb2e85cbd19eb03e617782d90d2c60e", "sport_key": "baseball_mlb", "sport_title": "MLB", "commence_time": "2026-07-17T23:16:00Z", "home_team": "Toronto Blue Jays", "away_team": "Chicago White Sox", "bookmakers": [{"key": "draftkings", "title": "DraftKings", "markets": [{"key": "pitcher_earned_runs", "last_update": "2026-07-18T00:01:30Z", "outcomes": [{"name": "Over", "description": "Anthony Kay", "price": 1.95, "point": 1.5}, {"name": "Under", "description": "Anthony Kay", "price": 1.77, "point": 1.5}]}, {"key": "pitcher_hits_allowed", "last_update": "2026-07-18T00:01:30Z", "outcomes": [{"name": "Over", "description": "Anthony Kay", "price": 2.0, "point": 3.5}, {"name": "Under", "description": "Anthony Kay", "price": 1.71, "point": 3.5}]}, {"key": "pitcher_outs", "last_update": "2026-07-18T00:01:30Z", "outcomes": [{"name": "Over", "description": "Anthony Kay", "price": 2.05, "point": 15.5}, {"name": "Under", "description": "Anthony Kay", "price": 1.69, "point": 15.5}]}, {"key": "pitcher_record_a_win", "last_update": "2026-07-18T00:01:30Z", "outcomes": [{"name": "Yes", "description": "Anthony Kay", "price": 1.5}, {"name": "No", "description": "Anthony Kay", "price": 2.25}]}, {"key": "pitcher_strikeouts", "last_update": "2026-07-18T00:01:30Z", "outcomes": [{"name": "Over", "description": "Anthony Kay", "price": 1.49, "point": 3.5}, {"name": "Under", "description": "Anthony Kay", "price": 2.5, "point": 3.5}]}, {"key": "pitcher_walks", "last_update": "2026-07-18T00:01:30Z", "outcomes": [{"name": "Over", "description": "Anthony Kay", "price": 2.55, "point": 2.5}, {"name": "Under", "description": "Anthony Kay", "price": 1.48, "point": 2.5}]}]}, {"key": "fanatics", "title": "Fanatics", "markets": [{"key": "pitcher_strikeouts", "last_update": "2026-07-18T00:00:45Z", "outcomes": [{"name": "Over", "description": "Anthony Kay", "price": 2.35, "point": 4.5}, {"name": "Under", "description": "Anthony Kay", "price": 1.56, "point": 4.5}]}]}, {"key": "williamhill_us", "title": "Caesars", "markets": [{"key": "pitcher_outs", "last_update": "2026-07-18T00:02:18Z", "outcomes": [{"name": "Over", "description": "Anthony Kay", "price": 2.03, "point": 15.5}, {"name": "Under", "description": "Anthony Kay", "price": 1.73, "point": 15.5}]}]}, {"key": "betmgm", "title": "BetMGM", "markets": [{"key": "pitcher_hits_allowed", "last_update": "2026-07-18T00:01:17Z", "outcomes": [{"name": "Over", "description": "Anthony Kay", "price": 2.0, "point": 3.5}, {"name": "Under", "description": "Anthony Kay", "price": 1.74, "point": 3.5}]}, {"key": "pitcher_strikeouts", "last_update": "2026-07-18T00:01:17Z", "outcomes": [{"name": "Over", "description": "Anthony Kay", "price": 2.2, "point": 4.5}, {"name": "Under", "description": "Anthony Kay", "price": 1.62, "point": 4.5}]}]}]}}