{"fetched_at": 1782608402.2758317, "data": {"timestamp": "2025-05-20T22:55:38Z", "previous_timestamp": "2025-05-20T22:50:37Z", "next_timestamp": "2025-05-20T23:00:37Z", "data": {"id": "78fe50f493f1a4bce96b8cbfdc4c7d1f", "sport_key": "basketball_wnba", "sport_title": "WNBA", "commence_time": "2025-05-20T23:00:00Z", "home_team": "Indiana Fever", "away_team": "Atlanta Dream", "bookmakers": [{"key": "fanduel", "title": "FanDuel", "last_update": "2025-05-20T22:53:53Z", "markets": [{"key": "player_threes", "last_update": "2025-05-20T22:54:48Z", "outcomes": [{"name": "Over", "description": "Allisha Gray", "price": 2.1, "point": 2.5}, {"name": "Under", "description": "Allisha Gray", "price": 1.68, "point": 2.5}, {"name": "Over", "description": "Kelsey Mitchell", "price": 2.22, "point": 2.5}, {"name": "Under", "description": "Kelsey Mitchell", "price": 1.62, "point": 2.5}, {"name": "Over", "description": "Rhyne Howard", "price": 2.1, "point": 3.5}, {"name": "Under", "description": "Rhyne Howard", "price": 1.68, "point": 3.5}, {"name": "Over", "description": "Caitlin Clark", "price": 1.89, "point": 3.5}, {"name": "Under", "description": "Caitlin Clark", "price": 1.85, "point": 3.5}, {"name": "Over", "description": "DeWanna Bonner", "price": 2.62, "point": 1.5}, {"name": "Under", "description": "DeWanna Bonner", "price": 1.45, "point": 1.5}]}]}, {"key": "betrivers", "title": "BetRivers", "last_update": "2025-05-20T22:55:05Z", "markets": [{"key": "player_threes", "last_update": "2025-05-20T22:55:04Z", "outcomes": [{"name": "Over", "description": "DeWanna Bonner", "price": 2.63, "point": 1.5}, {"name": "Over", "description": "Caitlin Clark", "price": 1.83, "point": 3.5}, {"name": "Over", "description": "Allisha Gray", "price": 2.08, "point": 2.5}, {"name": "Over", "description": "Rhyne Howard", "price": 2.1, "point": 3.5}, {"name": "Over", "description": "Kelsey Mitchell", "price": 2.04, "point": 2.5}]}]}, {"key": "betonlineag", "title": "BetOnline.ag", "last_update": "2025-05-20T22:55:06Z", "markets": [{"key": "player_threes", "last_update": "2025-05-20T22:55:26Z", "outcomes": [{"name": "Over", "description": "Allisha Gray", "price": 2.15, "point": 2.5}, {"name": "Under", "description": "Allisha Gray", "price": 1.67, "point": 2.5}, {"name": "Over", "description": "Rhyne Howard", "price": 2.1, "point": 3.5}, {"name": "Under", "description": "Rhyne Howard", "price": 1.7, "point": 3.5}, {"name": "Over", "description": "Kelsey Mitchell", "price": 2.1, "point": 2.5}, {"name": "Under", "description": "Kelsey Mitchell", "price": 1.7, "point": 2.5}, {"name": "Over", "description": "Caitlin Clark", "price": 2.0, "point": 3.5}, {"name": "Under", "description": "Caitlin Clark", "price": 1.77, "point": 3.5}, {"name": "Over", "description": "DeWanna Bonner", "price": 2.55, "point": 1.5}, {"name": "Under", "description": "DeWanna Bonner", "price": 1.49, "point": 1.5}, {"name": "Over", "description": "Natasha Howard", "price": 2.71, "point": 0.5}, {"name": "Under", "description": "Natasha Howard", "price": 1.44, "point": 0.5}, {"name": "Over", "description": "Aliyah Boston", "price": 3.39, "point": 0.5}, {"name": "Under", "description": "Aliyah Boston", "price": 1.3, "point": 0.5}]}]}, {"key": "draftkings", "title": "DraftKings", "last_update": "2025-05-20T22:55:05Z", "markets": [{"key": "player_threes", "last_update": "2025-05-20T22:55:23Z", "outcomes": [{"name": "Over", "description": "Caitlin Clark", "price": 1.91, "point": 3.5}, {"name": "Under", "description": "Caitlin Clark", "price": 1.83, "point": 3.5}, {"name": "Over", "description": "Rhyne Howard", "price": 2.1, "point": 3.5}, {"name": "Under", "description": "Rhyne Howard", "price": 1.67, "point": 3.5}, {"name": "Over", "description": "Kelsey Mitchell", "price": 2.05, "point": 2.5}, {"name": "Under", "description": "Kelsey Mitchell", "price": 1.71, "point": 2.5}]}]}, {"key": "bovada", "title": "Bovada", "last_update": "2025-05-20T22:55:05Z", "markets": [{"key": "player_threes", "last_update": "2025-05-20T22:55:06Z", "outcomes": [{"name": "Over", "description": "Caitlin Clark", "price": 1.95, "point": 3.5}, {"name": "Under", "description": "Caitlin Clark", "price": 1.8, "point": 3.5}, {"name": "Over", "description": "Rhyne Howard", "price": 2.15, "point": 3.5}, {"name": "Under", "description": "Rhyne Howard", "price": 1.67, "point": 3.5}, {"name": "Over", "description": "Kelsey Mitchell", "price": 2.05, "point": 2.5}, {"name": "Under", "description": "Kelsey Mitchell", "price": 1.74, "point": 2.5}]}]}, {"key": "betmgm", "title": "BetMGM", "last_update": "2025-05-20T22:55:05Z", "markets": [{"key": "player_threes", "last_update": "2025-05-20T22:55:45Z", "outcomes": [{"name": "Over", "description": "DeWanna Bonner", "price": 2.6, "point": 1.5}, {"name": "Under", "description": "DeWanna Bonner", "price": 1.48, "point": 1.5}, {"name": "Over", "description": "Kelsey Mitchell", "price": 2.05, "point": 2.5}, {"name": "Under", "description": "Kelsey Mitchell", "price": 1.74, "point": 2.5}, {"name": "Over", "description": "Allisha Gray", "price": 2.05, "point": 2.5}, {"name": "Under", "description": "Allisha Gray", "price": 1.74, "point": 2.5}, {"name": "Over", "description": "Caitlin Clark", "price": 1.83, "point": 3.5}, {"name": "Under", "description": "Caitlin Clark", "price": 1.91, "point": 3.5}, {"name": "Over", "description": "Rhyne Howard", "price": 2.05, "point": 3.5}, {"name": "Under", "description": "Rhyne Howard", "price": 1.74, "point": 3.5}, {"name": "Over", "description": "Natasha Howard", "price": 2.3, "point": 0.5}, {"name": "Under", "description": "Natasha Howard", "price": 1.61, "point": 0.5}]}]}]}}}