{"date": "2025-07-12", "pk": 777136, "home": {"team_id": 118, "starter_id": 672582, "lineup": [[663697, "Jonathan India", 1], [677951, "Bobby Witt Jr.", 2], [686469, "Vinnie Pasquantino", 3], [672580, "Maikel Garcia", 4], [521692, "Salvador Perez", 5], [695506, "Jac Caglianone", 6], [679845, "Nick Loftin", 7], [670231, "John Rave", 8], [664728, "Kyle Isbel", 9]], "stats": {"663697": {"pa": 4, "pts": 12, "hr": 0, "bb": 0}, "521692": {"pa": 4, "pts": 2, "hr": 0, "bb": 1}, "679845": {"pa": 3, "pts": 2, "hr": 0, "bb": 0}, "670231": {"pa": 3, "pts": 0, "hr": 0, "bb": 0}, "686469": {"pa": 4, "pts": 3, "hr": 0, "bb": 0}, "664728": {"pa": 3, "pts": 7, "hr": 0, "bb": 0}, "672580": {"pa": 4, "pts": 0, "hr": 0, "bb": 0}, "695506": {"pa": 4, "pts": 0, "hr": 0, "bb": 0}, "677951": {"pa": 4, "pts": 2, "hr": 0, "bb": 1}}}, "away": {"team_id": 121, "starter_id": 593423, "lineup": [[607043, "Brandon Nimmo", 1], [596019, "Francisco Lindor", 2], [665742, "Juan Soto", 3], [624413, "Pete Alonso", 4], [668901, "Mark Vientos", 5], [643446, "Jeff McNeil", 6], [621438, "Tyrone Taylor", 7], [683146, "Brett Baty", 8], [620443, "Luis Torrens", 9]], "stats": {"620443": {"pa": 3, "pts": 5, "hr": 0, "bb": 0}, "621438": {"pa": 4, "pts": 0, "hr": 0, "bb": 0}, "643446": {"pa": 4, "pts": 5, "hr": 0, "bb": 0}, "668901": {"pa": 3, "pts": 3, "hr": 0, "bb": 0}, "682668": {"pa": 1, "pts": 0, "hr": 0, "bb": 0}, "683146": {"pa": 3, "pts": 0, "hr": 0, "bb": 0}, "624413": {"pa": 4, "pts": 7, "hr": 0, "bb": 0}, "596019": {"pa": 4, "pts": 10, "hr": 0, "bb": 0}, "607043": {"pa": 4, "pts": 2, "hr": 0, "bb": 1}, "665742": {"pa": 4, "pts": 16, "hr": 1, "bb": 0}}}}