{"date": "2025-07-07", "pk": 777209, "home": {"team_id": 111, "starter_id": 690916, "lineup": [[681987, "Nate Eaton", 1], [663853, "Romy Gonzalez", 2], [701350, "Roman Anthony", 3], [608701, "Rob Refsnyder", 4], [596115, "Trevor Story", 5], [665966, "Carlos Narv\u00e1ez", 6], [677800, "Wilyer Abreu", 7], [647351, "Abraham Toro", 8], [678882, "Ceddanne Rafaela", 9]], "stats": {"701350": {"pa": 5, "pts": 24, "hr": 1, "bb": 0}, "663853": {"pa": 5, "pts": 24, "hr": 1, "bb": 0}, "608701": {"pa": 3, "pts": 10, "hr": 0, "bb": 1}, "596115": {"pa": 4, "pts": 2, "hr": 0, "bb": 0}, "677800": {"pa": 4, "pts": 12, "hr": 0, "bb": 0}, "647351": {"pa": 4, "pts": 9, "hr": 0, "bb": 0}, "665966": {"pa": 4, "pts": 10, "hr": 0, "bb": 0}, "681987": {"pa": 3, "pts": 5, "hr": 0, "bb": 0}, "680776": {"pa": 1, "pts": 7, "hr": 0, "bb": 0}, "678882": {"pa": 4, "pts": 14, "hr": 1, "bb": 0}, "691785": {"pa": 2, "pts": 0, "hr": 0, "bb": 0}}}, "away": {"team_id": 115, "starter_id": 596295, "lineup": [[671289, "Tyler Freeman", 1], [696100, "Hunter Goodman", 2], [666160, "Mickey Moniak", 3], [642731, "Thairo Estrada", 4], [669911, "Michael Toglia", 5], [641857, "Ryan McMahon", 6], [686668, "Brenton Doyle", 7], [692585, "Yanquiel Fern\u00e1ndez", 8], [690022, "Ryan Ritter", 9]], "stats": {"666160": {"pa": 3, "pts": 5, "hr": 0, "bb": 0}, "642731": {"pa": 4, "pts": 9, "hr": 0, "bb": 0}, "669911": {"pa": 4, "pts": 4, "hr": 0, "bb": 1}, "641857": {"pa": 4, "pts": 10, "hr": 0, "bb": 0}, "671289": {"pa": 5, "pts": 8, "hr": 0, "bb": 1}, "692585": {"pa": 2, "pts": 0, "hr": 0, "bb": 0}, "690022": {"pa": 4, "pts": 2, "hr": 0, "bb": 1}, "696100": {"pa": 4, "pts": 0, "hr": 0, "bb": 0}, "571657": {"pa": 2, "pts": 0, "hr": 0, "bb": 0}, "687597": {"pa": 1, "pts": 0, "hr": 0, "bb": 0}, "686668": {"pa": 4, "pts": 5, "hr": 0, "bb": 0}}}}