{"date": "2025-06-09", "pk": 777581, "home": {"team_id": 138, "starter_id": 669467, "lineup": [[663457, "Lars Nootbaar", 1], [691026, "Masyn Winn", 2], [680977, "Brendan Donovan", 3], [575929, "Willson Contreras", 4], [671056, "Iv\u00e1n Herrera", 5], [571448, "Nolan Arenado", 6], [676475, "Alec Burleson", 7], [669357, "Nolan Gorman", 8], [687363, "Victor Scott II", 9]], "stats": {"669357": {"pa": 2, "pts": 3, "hr": 0, "bb": 0}, "687363": {"pa": 4, "pts": 4, "hr": 0, "bb": 1}, "575929": {"pa": 4, "pts": 11, "hr": 0, "bb": 2}, "571448": {"pa": 4, "pts": 0, "hr": 0, "bb": 0}, "663457": {"pa": 5, "pts": 0, "hr": 0, "bb": 0}, "668723": {"pa": 2, "pts": 0, "hr": 0, "bb": 0}, "676475": {"pa": 4, "pts": 5, "hr": 0, "bb": 0}, "680977": {"pa": 5, "pts": 3, "hr": 0, "bb": 0}, "691026": {"pa": 5, "pts": 5, "hr": 0, "bb": 0}, "671056": {"pa": 4, "pts": 21, "hr": 1, "bb": 0}}}, "away": {"team_id": 141, "starter_id": 621244, "lineup": [[666182, "Bo Bichette", 1], [665489, "Vladimir Guerrero Jr.", 2], [680718, "Addison Barger", 3], [672386, "Alejandro Kirk", 4], [543807, "George Springer", 5], [665926, "Andr\u00e9s Gim\u00e9nez", 6], [676914, "Davis Schneider", 7], [676391, "Ernie Clement", 8], [682729, "Jonatan Clase", 9]], "stats": {"666182": {"pa": 5, "pts": 5, "hr": 0, "bb": 0}, "682729": {"pa": 4, "pts": 17, "hr": 1, "bb": 0}, "676391": {"pa": 5, "pts": 7, "hr": 0, "bb": 0}, "665926": {"pa": 5, "pts": 3, "hr": 0, "bb": 0}, "676914": {"pa": 3, "pts": 2, "hr": 0, "bb": 1}, "664770": {"pa": 2, "pts": 2, "hr": 0, "bb": 1}, "680718": {"pa": 5, "pts": 7, "hr": 0, "bb": 0}, "543807": {"pa": 5, "pts": 9, "hr": 0, "bb": 1}, "665489": {"pa": 5, "pts": 8, "hr": 0, "bb": 0}, "672386": {"pa": 5, "pts": 29, "hr": 1, "bb": 0}}}}