{"date": "2025-06-06", "pk": 777614, "home": {"team_id": 108, "starter_id": 543294, "lineup": [[687263, "Zach Neto", 1], [694384, "Nolan Schanuel", 2], [545361, "Mike Trout", 3], [621493, "Taylor Ward", 4], [624585, "Jorge Soler", 5], [518595, "Travis d'Arnaud", 6], [650859, "Luis Rengifo", 7], [666176, "Jo Adell", 8], [621035, "Chris Taylor", 9]], "stats": {"650859": {"pa": 3, "pts": 0, "hr": 0, "bb": 0}, "621035": {"pa": 3, "pts": 19, "hr": 0, "bb": 0}, "687263": {"pa": 4, "pts": 13, "hr": 0, "bb": 0}, "624585": {"pa": 4, "pts": 5, "hr": 0, "bb": 0}, "518595": {"pa": 4, "pts": 19, "hr": 1, "bb": 0}, "621493": {"pa": 4, "pts": 2, "hr": 0, "bb": 1}, "545361": {"pa": 4, "pts": 0, "hr": 0, "bb": 0}, "666176": {"pa": 3, "pts": 4, "hr": 0, "bb": 0}, "694384": {"pa": 4, "pts": 5, "hr": 0, "bb": 0}}}, "away": {"team_id": 136, "starter_id": 682243, "lineup": [[641487, "J.P. Crawford", 1], [593871, "Jorge Polanco", 2], [677594, "Julio Rodr\u00edguez", 3], [663728, "Cal Raleigh", 4], [668227, "Randy Arozarena", 5], [642133, "Rowdy Tellez", 6], [665750, "Leody Taveras", 7], [702284, "Cole Young", 8], [810938, "Ben Williamson", 9]], "stats": {"702284": {"pa": 4, "pts": 0, "hr": 0, "bb": 0}, "668227": {"pa": 4, "pts": 4, "hr": 0, "bb": 2}, "641487": {"pa": 5, "pts": 5, "hr": 0, "bb": 0}, "665750": {"pa": 4, "pts": 2, "hr": 0, "bb": 0}, "642133": {"pa": 3, "pts": 5, "hr": 0, "bb": 0}, "663728": {"pa": 4, "pts": 12, "hr": 0, "bb": 1}, "670156": {"pa": 1, "pts": 0, "hr": 0, "bb": 0}, "664238": {"pa": 1, "pts": 0, "hr": 0, "bb": 0}, "677594": {"pa": 4, "pts": 20, "hr": 0, "bb": 0}, "810938": {"pa": 3, "pts": 17, "hr": 0, "bb": 0}, "593871": {"pa": 4, "pts": 3, "hr": 0, "bb": 0}}}}