{"date": "2025-06-04", "pk": 777651, "home": {"team_id": 141, "starter_id": 621244, "lineup": [[666182, "Bo Bichette", 1], [665489, "Vladimir Guerrero Jr.", 2], [680718, "Addison Barger", 3], [672386, "Alejandro Kirk", 4], [543807, "George Springer", 5], [664770, "Nathan Lukes", 6], [702176, "Alan Roden", 7], [682729, "Jonatan Clase", 8], [665926, "Andr\u00e9s Gim\u00e9nez", 9]], "stats": {"666182": {"pa": 4, "pts": 10, "hr": 0, "bb": 0}, "682729": {"pa": 3, "pts": 0, "hr": 0, "bb": 0}, "676391": {"pa": 1, "pts": 0, "hr": 0, "bb": 0}, "665926": {"pa": 3, "pts": 8, "hr": 0, "bb": 0}, "702176": {"pa": 2, "pts": 0, "hr": 0, "bb": 0}, "664770": {"pa": 2, "pts": 0, "hr": 0, "bb": 0}, "680718": {"pa": 4, "pts": 0, "hr": 0, "bb": 0}, "543807": {"pa": 3, "pts": 0, "hr": 0, "bb": 0}, "665489": {"pa": 4, "pts": 10, "hr": 0, "bb": 0}, "664702": {"pa": 1, "pts": 0, "hr": 0, "bb": 0}, "672386": {"pa": 4, "pts": 7, "hr": 0, "bb": 0}}}, "away": {"team_id": 143, "starter_id": 690953, "lineup": [[681082, "Bryson Stott", 1], [607208, "Trea Turner", 2], [547180, "Bryce Harper", 3], [656941, "Kyle Schwarber", 4], [664761, "Alec Bohm", 5], [592206, "Nick Castellanos", 6], [596146, "Max Kepler", 7], [592663, "J.T. Realmuto", 8], [669016, "Brandon Marsh", 9]], "stats": {"669016": {"pa": 2, "pts": 5, "hr": 0, "bb": 1}, "547180": {"pa": 4, "pts": 0, "hr": 0, "bb": 0}, "592663": {"pa": 3, "pts": 3, "hr": 0, "bb": 0}, "642215": {"pa": 1, "pts": 0, "hr": 0, "bb": 0}, "592206": {"pa": 4, "pts": 14, "hr": 1, "bb": 0}, "664761": {"pa": 4, "pts": 3, "hr": 0, "bb": 0}, "681082": {"pa": 4, "pts": 0, "hr": 0, "bb": 0}, "656941": {"pa": 4, "pts": 3, "hr": 0, "bb": 0}, "596146": {"pa": 3, "pts": 2, "hr": 0, "bb": 1}, "607208": {"pa": 4, "pts": 0, "hr": 0, "bb": 0}}}}